pollstats/__init__.py
pollstats/admin.py
pollstats/apps.py
pollstats/models.py
pollstats/tests.py
pollstats/urls.py
pollstats/views.py
pollstats/migrations/__init__.py
pollstats/static/pollstatsassets/css/style.css
pollstats/static/pollstatsassets/img/about.jpg
pollstats/static/pollstatsassets/img/apple-touch-icon.png
pollstats/static/pollstatsassets/img/favicon.png
pollstats/static/pollstatsassets/img/features-2.png
pollstats/static/pollstatsassets/img/features-3.png
pollstats/static/pollstatsassets/img/features.png
pollstats/static/pollstatsassets/img/footer-bg.png
pollstats/static/pollstatsassets/img/hero-bg.png
pollstats/static/pollstatsassets/img/hero-img.png
pollstats/static/pollstatsassets/img/hero-img.svg
pollstats/static/pollstatsassets/img/logo.png
pollstats/static/pollstatsassets/img/pricing-business.png
pollstats/static/pollstatsassets/img/pricing-free.png
pollstats/static/pollstatsassets/img/pricing-starter.png
pollstats/static/pollstatsassets/img/pricing-ultimate.png
pollstats/static/pollstatsassets/img/team-shape.svg
pollstats/static/pollstatsassets/img/values-1.png
pollstats/static/pollstatsassets/img/values-2.png
pollstats/static/pollstatsassets/img/values-3.png
pollstats/static/pollstatsassets/img/blog/blog-1.jpg
pollstats/static/pollstatsassets/img/blog/blog-2.jpg
pollstats/static/pollstatsassets/img/blog/blog-3.jpg
pollstats/static/pollstatsassets/img/blog/blog-4.jpg
pollstats/static/pollstatsassets/img/blog/blog-author.jpg
pollstats/static/pollstatsassets/img/blog/blog-inside-post.jpg
pollstats/static/pollstatsassets/img/blog/blog-recent-1.jpg
pollstats/static/pollstatsassets/img/blog/blog-recent-2.jpg
pollstats/static/pollstatsassets/img/blog/blog-recent-3.jpg
pollstats/static/pollstatsassets/img/blog/blog-recent-4.jpg
pollstats/static/pollstatsassets/img/blog/blog-recent-5.jpg
pollstats/static/pollstatsassets/img/blog/comments-1.jpg
pollstats/static/pollstatsassets/img/blog/comments-2.jpg
pollstats-0.6.dist-info/LICENSE
pollstats-0.6.dist-info/METADATA
pollstats-0.6.dist-info/WHEEL
pollstats-0.6.dist-info/top_level.txt
pollstats-0.6.dist-info/RECORD
