Metadata-Version: 2.1
Name: pollstats
Version: 0.6
Summary: A short description of your package
Home-page: https://github.com/Vijayanand-debug/pollstats
Author: Vijayanand
Author-email: vijayanand563@gmail.com
License: UNKNOWN
Platform: UNKNOWN
Classifier: Development Status :: 3 - Alpha
Classifier: Intended Audience :: Developers
Classifier: License :: OSI Approved :: MIT License
Classifier: Programming Language :: Python :: 3
Classifier: Programming Language :: Python :: 3.6
Classifier: Programming Language :: Python :: 3.7
Classifier: Programming Language :: Python :: 3.8
Classifier: Programming Language :: Python :: 3.9
License-File: LICENSE
